pytest_mitmproxy_plugin/__init__.py
pytest_mitmproxy_plugin/abstract_addon.py
pytest_mitmproxy_plugin/log_step.py
pytest_mitmproxy_plugin/mitm_manager.py
pytest_mitmproxy_plugin/plugin.py
pytest_mitmproxy_plugin/py.typed
pytest_mitmproxy_plugin-0.1.0.dist-info/LICENSE
pytest_mitmproxy_plugin-0.1.0.dist-info/METADATA
pytest_mitmproxy_plugin-0.1.0.dist-info/WHEEL
pytest_mitmproxy_plugin-0.1.0.dist-info/entry_points.txt
pytest_mitmproxy_plugin-0.1.0.dist-info/RECORD
