Metadata-Version: 2.3
Name: pytest-mitmproxy-plugin
Version: 0.1.0
Summary: Use MITM Proxy in autotests with full control from code
License: The MIT License (MIT)
Author: Vladislav Metel
Author-email: metel.vlad@gmail.com
Maintainer: Vladislav Metel
Maintainer-email: metel.vlad@gmail.com
Requires-Python: >=3.11
Classifier: Framework :: Pytest
Classifier: Development Status :: 4 - Beta
Classifier: Intended Audience :: Developers
Classifier: Topic :: Software Development :: Testing
Classifier: Operating System :: OS Independent
Classifier: Programming Language :: Python
Classifier: Programming Language :: Python :: 3.11
Classifier: Programming Language :: Python :: 3.12
Classifier: Programming Language :: Python :: 3.13
Classifier: Programming Language :: Python :: 3 :: Only
Classifier: Programming Language :: Python :: Implementation :: CPython
Classifier: Programming Language :: Python :: Implementation :: PyPy
Classifier: License :: OSI Approved :: MIT License
Provides-Extra: allure
Requires-Dist: allure-pytest (>=2.13.3,<3.0.0) ; extra == "allure"
Requires-Dist: allure-python-commons (>=2.13.3,<3.0.0) ; extra == "allure"
Requires-Dist: mitmproxy (>=11.0.2)
Requires-Dist: pytest (>=7.2.0)
Requires-Dist: tox (>=4.24.1,<5.0.0)
Project-URL: Repository, https://github.com/IamVladislav/pytest-mitmproxy-plugin
